concretefhe_common-0.0.10-py3.9-nspkg.pth
concretefhe/common/__init__.py
concretefhe/common/file.py
concretefhe_common-0.0.10.dist-info/LICENSE
concretefhe_common-0.0.10.dist-info/METADATA
concretefhe_common-0.0.10.dist-info/WHEEL
concretefhe_common-0.0.10.dist-info/namespace_packages.txt
concretefhe_common-0.0.10.dist-info/top_level.txt
concretefhe_common-0.0.10.dist-info/RECORD
